MyPythonLibrary/__init__.py
MyPythonLibrary/thefuncs.py
MyExtraPythonLibrary-1.0.dist-info/METADATA
MyExtraPythonLibrary-1.0.dist-info/WHEEL
MyExtraPythonLibrary-1.0.dist-info/top_level.txt
MyExtraPythonLibrary-1.0.dist-info/RECORD
