Metadata-Version: 2.1
Name: MyExtraPythonLibrary
Version: 1.0
Summary: My first ever python libros
Home-page: UNKNOWN
Author: Jacketh Davieth
License: MIT
Platform: UNKNOWN
